wsgi_lithium/__init__.py
wsgi_lithium/gunicorn_utils.py
wsgi_lithium-0.3.0.dist-info/entry_points.txt
wsgi_lithium-0.3.0.dist-info/LICENSE
wsgi_lithium-0.3.0.dist-info/WHEEL
wsgi_lithium-0.3.0.dist-info/METADATA
wsgi_lithium-0.3.0.dist-info/RECORD
