Metadata-Version: 2.1
Name: wsgi_lithium
Version: 0.3.0
Summary: An HTTP to WSGI server that relies on Python's included batteries
Author-email: Léo El Amri <leo@superlel.me>
Requires-Python: >=3.7
Classifier: License :: OSI Approved :: MIT License
Project-URL: repository, https://github.com/lel-amri/wsgi-lithium
